api_limit/__init__.py
api_limit/algorithm.py
api_limit/main.py
api_limit-0.0.2.dist-info/METADATA
api_limit-0.0.2.dist-info/WHEEL
api_limit-0.0.2.dist-info/top_level.txt
api_limit-0.0.2.dist-info/RECORD
