Metadata-Version: 2.1
Name: api-limit
Version: 0.0.2
Summary: API rate limit decorator
Home-page: UNKNOWN
License: UNKNOWN
Platform: UNKNOWN
